{
  "$schema": "https://static.modelcontextprotocol.io/schemas/2025-12-11/server.schema.json",
  "name": "io.github.jacksenechal/scan-mcp",
  "description": "MCP server for scanner discovery and batch capture via SANE",
  "websiteUrl": "https://github.com/jacksenechal/scan-mcp",
  "repository": {
    "url": "https://github.com/jacksenechal/scan-mcp",
    "source": "github"
  },
  "version": "0.3.0",
  "packages": [
    {
      "registryType": "npm",
      "registryBaseUrl": "https://registry.npmjs.org",
      "identifier": "scan-mcp",
      "version": "0.3.0",
      "transport": {
        "type": "stdio"
      }
    }
  ]
}
